s3ben/__init__.py
s3ben/arguments.py
s3ben/backup.py
s3ben/cli.py
s3ben/config.py
s3ben/constants.py
s3ben/decorators.py
s3ben/helpers.py
s3ben/logger.py
s3ben/progress.py
s3ben/rabbit.py
s3ben/remapper.py
s3ben/s3.py
s3ben/sentry.py
s3ben/ui.py
s3ben-0.11.0.dist-info/METADATA
s3ben-0.11.0.dist-info/WHEEL
s3ben-0.11.0.dist-info/entry_points.txt
s3ben-0.11.0.dist-info/RECORD
