Metadata-Version: 2.1
Name: s3ben
Version: 0.11.0
Summary: S3 bucket backup using notification
Author: Arunas Grigalionis
Author-email: arunas.grigalionis@gmail.com
Requires-Python: >=3.9,<4.0
Classifier: Programming Language :: Python :: 3
Classifier: Programming Language :: Python :: 3.9
Classifier: Programming Language :: Python :: 3.10
Classifier: Programming Language :: Python :: 3.11
Classifier: Programming Language :: Python :: 3.12
Requires-Dist: boto3 (>=1.35.16,<2.0.0)
Requires-Dist: boto3-stubs[s3] (>=1.35.37,<2.0.0)
Requires-Dist: pika (>=1.3.2,<2.0.0)
Requires-Dist: rgwadmin (>=2.4.5,<3.0.0)
Requires-Dist: sentry-sdk (>=2.14.0,<3.0.0)
Requires-Dist: tabulate (>=0.9.0,<0.10.0)
Requires-Dist: typing-extensions (>=4.12.2,<5.0.0)
